qbase/__init__.py
qbase/common/__init__.py
qbase/common/configer.py
qbase/common/loger.py
qbase/common/mmaper.py
qbase/common/mySql.py
qbase/common/until.py
qbase/dao/__init__.py
qbase/dao/accountMapper.py
qbase/dao/bitmexResultMapper.py
qbase/dao/huobiResultMapper.py
qbase/dao/okexResultMapper.py
qbase/dao/positionMapper.py
qbase/entity/__init__.py
qbase/entity/signal.py
qbase/enum/__init__.py
qbase/enum/enum.py
qbase/huobi/__init__.py
qbase/huobi/huobiData.py
qbase/huobi/huobiService.py
qbase/okex/__init__.py
qbase/okex/httpMD5Util.py
qbase/okex/okcoinFutureAPI.py
qbase/okex/okcoinSpotAPI.py
qbase/okex/okexData.py
qbase/threading/__init__.py
qbase/threading/accountMain.py
qbase/threading/transaction.py
qbase/transaction/__init__.py
qbase/transaction/transactions.py
qbase-1.0.7.dist-info/METADATA
qbase-1.0.7.dist-info/RECORD
qbase-1.0.7.dist-info/WHEEL
qbase-1.0.7.dist-info/top_level.txt
