Metadata-Version: 2.1
Name: qbase
Version: 1.0.7
Summary: qq based programe for fun
Home-page: https://gitlab.com/jdjshx/quanti-frame.git
Author: lijialun
Author-email: cslijialun@126.com
License: Apache License, Version 2.0
Platform: UNKNOWN
Classifier: Development Status :: 4 - Beta
Classifier: Intended Audience :: Developers
Classifier: Intended Audience :: System Administrators
Classifier: License :: OSI Approved :: Apache Software License
Classifier: Operating System :: MacOS :: MacOS X
Classifier: Operating System :: Microsoft :: Windows
Classifier: Operating System :: POSIX
Classifier: Programming Language :: Python
Classifier: Topic :: Software Development :: Libraries :: Python Modules
Classifier: Topic :: Utilities
Requires-Dist: requests (>=2.0.0)
Requires-Dist: pymysql
Requires-Dist: pandas
Requires-Dist: websocket
